{"cameraMode":{"drawMode":0,"name":"Shaded","section":"Shading Mode"},"sceneLighting":true,"audioPlay":false,"sceneViewState":{"m_AlwaysRefresh":false,"showFog":true,"showSkybox":true,"showFlares":true,"showImageEffects":true,"showParticleSystems":true,"showVisualEffectGraphs":true,"m_FxEnabled":true},"in2DMode":false,"pivot":{"x":5.323379039764404,"y":12.019262313842774,"z":-10.000243186950684},"rotation":{"x":-0.11602242290973664,"y":-0.5636740922927856,"z":0.08039306104183197,"w":-0.8141223788261414},"size":60.45311737060547,"orthographic":false}